hello_open_source_robcamp_code/__init__.py
hello_open_source_robcamp_code/main.py
hello_open_source-0.1.1.dist-info/LICENSE
hello_open_source-0.1.1.dist-info/METADATA
hello_open_source-0.1.1.dist-info/WHEEL
hello_open_source-0.1.1.dist-info/top_level.txt
hello_open_source-0.1.1.dist-info/RECORD
