Metadata-Version: 2.2
Name: hello_open_source
Version: 0.1.1
Summary: this is a tutorial on how to build an open source project
Author-email: Robert Campbell <robert@coach-alliance.com>
Project-URL: Homepage, https://github.com/pypa/sampleproject
Project-URL: Issues, https://github.com/pypa/sampleproject/issues
Requires-Python: >=3.8
License-File: LICENSE
